{
  "name": "CAH Family Pack",
  "blackCards": [
    {
      "text": "with _____."
    },
    {
      "text": "Do you see _____?"
    },
    {
      "text": "from _____."
    },
    {
      "text": "That's just _____."
    },
    {
      "text": "time for _____!"
    },
    {
      "text": "you try _____."
    },
    {
      "text": "against _____."
    },
    {
      "text": "Captain _____"
    },
    {
      "text": "It's called \"_____.\""
    },
    {
      "text": "\"Portrait of _____.\""
    },
    {
      "text": "They want _____."
    },
    {
      "text": "\"Mr. _____.\""
    },
    {
      "text": "There's _____"
    },
    {
      "text": "now _____."
    },
    {
      "text": "it's Tommy \"_____\""
    },
    {
      "text": "Just _____."
    },
    {
      "text": "smells like _____."
    },
    {
      "text": "I'm _____."
    },
    {
      "text": "for _____!"
    },
    {
      "text": "allow _____"
    },
    {
      "text": "and _____."
    },
    {
      "text": "We're into _____"
    },
    {
      "text": "He's _____."
    },
    {
      "text": "\"_____asaurus.\""
    },
    {
      "text": "I prefer _____."
    },
    {
      "text": "of _____!"
    },
    {
      "text": "vids of _____,"
    },
    {
      "text": "option is _____."
    },
    {
      "text": "\"_____ ball.\""
    },
    {
      "text": "Moms love _____.Where do babies"
    },
    {
      "text": "DESTROY _____."
    },
    {
      "text": "I'm \"_____ Mandy.\""
    },
    {
      "text": "It's _____!"
    },
    {
      "text": "\"_____ on Ice.\""
    },
    {
      "text": "she's _____."
    },
    {
      "text": "_____ accident."
    },
    {
      "text": "have _____."
    },
    {
      "text": "I'm _____!"
    },
    {
      "text": "it's _____ Barbie!"
    },
    {
      "text": "Game of _____."
    },
    {
      "text": "by _____."
    },
    {
      "text": "_____? Yes!"
    },
    {
      "text": "ME WANT _____."
    },
    {
      "text": "Rise of _____.\""
    },
    {
      "text": "I fight for _____!"
    },
    {
      "text": "try _____?"
    }
  ],
  "whiteCards": [
    "Climbing into a cow's butt.",
    "Literally ruining my life.",
    "They call me CHUNGO FEEL SICK.",
    "CHUNGO NO LIKE ANYMORE.",
    "You have to come pick me up!",
    "My parents keep in there.",
    "I'm not like the other children.",
    "CHUNGO ANGRY.",
    "It's SCARY.",
    "ME HUNGRY.",
    "A cloud that rains diarrhea.",
    "A caveperson named Helen.",
    "Acting kinda sus.",
    "All of your teeth falling out.",
    "Beautiful Grandma.",
    "Defecating on the neighbor's lawn.",
    "Eight hours of video games.",
    "Going night-night.",
    "Hanging out with Zendaya.",
    "Kissing Mom on the lips.",
    "Playing trumpet for the Mayor.",
    "Ratzilla.",
    "Teeny tiny turds.",
    "That there tarantula.",
    "The way Grandpa smells.",
    "Three glasses of red wine.",
    "Whatever Dad does at work.",
    "Getting shot out of a cannon.",
    "Jesus.",
    "Eating pasta out of my pants.",
    "A burrito smoothie.",
    "A bear.",
    "Old people.",
    "My sister's stupid boyfriend.",
    "Stuffing my underwear with pancakes.",
    "My chainsaw.",
    "Diarrhea.",
    "Boogers.",
    "The police.",
    "Sniffing a dog's butt.",
    "Horrible allergies.",
    "Your face.",
    "Rated-R stuff.",
    "Blowing up the Moon.",
    "Getting launched into space.",
    "A bird pooping on the president's head.",
    "Hot gossip.",
    "Forgetting to put on underwear.",
    "Running full speed into a wall.",
    "The Russians.",
    "A black hole.",
    "Putting my butt on stuff.",
    "Making the bees angry.",
    "A Democrat.",
    "Cheeto fingers.",
    "A huge honkin' carrot.",
    "The country of Bolivia.",
    "My parents.",
    "Idiots.",
    "Filling my butt with spaghetti.",
    "Work.",
    "Mashing a banana into your belly button.",
    "China.",
    "Shrek.",
    "Cavities.",
    "Eating people.",
    "Butts of all shapes and sizes.",
    "A 40-piece Chicken McNuggets.",
    "Climate change.",
    "Barf.",
    "A poop as big as Mom.",
    "A couch that eats children.",
    "Going to Hell.",
    "Fat stacks of cash.",
    "Dora the Explorer.",
    "Illegal drugs.",
    "Dad's meatloaf.",
    "Extra-warm Pepsi.",
    "Calling 9-1-1.",
    "Spending my parents' hard-earned money.",
    "Hot lava.",
    "Butt surgery.",
    "Freeing all the animals from the zoo.",
    "A bountiful harvest of squashes and corns.",
    "Bombs.",
    "Boobies.",
    "Respecting personal boundaries.",
    "Having no idea what's going on.",
    "John Wilkes Booth.",
    "Getting married.",
    "Politics.",
    "Garbage.",
    "Naked people.",
    "This stupid game.",
    "Biting a rich person.",
    "Screaming at birds.",
    "Getting stuck in the toilet.",
    "Getting crushed by a piano.",
    "Huge pants.",
    "Mom's spaghetti.",
    "A corn dog.",
    "Hot wet garbage.",
    "Principal Butthead.",
    "A statue of a naked guy.",
    "Joining the army.",
    "Witchcraft.",
    "Taking out my eyeballs.",
    "Sacrificing Uncle Tim.",
    "Moving to Ohio.",
    "A hundred screaming monkeys.",
    "Emotions.",
    "Ham.",
    "Clams.",
    "Spider-Man.",
    "Trying to catch that dang raccoon.",
    "Slapping my huge belly.",
    "The doll that watches me sleep.",
    "Money.",
    "LeBron James.",
    "Divorce.",
    "Salmon.",
    "Screaming the F-word.",
    "A whole thing of cottage cheese.",
    "Mayonnaise.",
    "Total world domination.",
    "Failure.",
    "JoJo Siwa.",
    "Getting kicked in the nuts.",
    "Farting and walking away.",
    "Sharks with legs.",
    "Triangles.",
    "Ninjas.",
    "The floor.",
    "The whole family.",
    "Bench pressing a horse.",
    "Spiders.",
    "Uranus.",
    "A Republican.",
    "Giving wedgies to my haters.",
    "\"Baby Shark\" on repeat forever.",
    "Big Randy.",
    "Blasting my math teacher into the sun.",
    "Dreaming about boys.",
    "Crying in the bathroom.",
    "Happiness.",
    "Poison.",
    "A scoop of tuna.",
    "Doing karate.",
    "Eating bicycles to somehow become famous.",
    "Lil Nas X.",
    "Dad's famous poops.",
    "Squirty cheese.",
    "Having too many fingers.",
    "Slapping that butt.",
    "Questioning authority.",
    "Farting a lot today.",
    "Going bald.",
    "Germs.",
    "Nuclear war.",
    "Barfing into a popcorn bucket.",
    "A cursed llama with no eyes.",
    "The wettest fart you ever heard.",
    "Shaving Dad's back.",
    "Overthrowing the government.",
    "Murdering.",
    "Exploding.",
    "Bleeding.",
    "The oppressive system of capitalism.",
    "A balloon filled with chili.",
    "Stealing dead bodies from the morgue.",
    "The freedom of speech.",
    "Egg salad.",
    "Rich people.",
    "Pirate music.",
    "Being a dinosaur.",
    "A fake kid made out of wood.",
    "Homework.",
    "Batman.",
    "A dead body.",
    "Drinking a whole bottle of ranch.",
    "Destroying the planet.",
    "Living in a pineapple under the sea.",
    "This pumpkin.",
    "Extremely tight underpants.",
    "Magical corn that makes you fart rainbows.",
    "Complaining.",
    "Bursting into flames.",
    "Poop from the sky.",
    "The humble earthworm.",
    "The garbage man.",
    "Your mom!",
    "The octopus stuck to my face.",
    "Dying of old age.",
    "Pantaloons.",
    "Screaming into a can of Pringles.",
    "Grandpa.",
    "Shutting up.",
    "Silence.",
    "My annoying brother.",
    "My future husband.",
    "Sitting on the toilet and going poop.",
    "A screaming soccer dad.",
    "Cocktail weenies.",
    "The British.",
    "WAR!",
    "Science.",
    "Picking my nose and eating it.",
    "Having a really big head.",
    "A dead whale.",
    "The power of the Dark Side.",
    "Big butt cheeks filled with poop.",
    "My friend Steve.",
    "Violence.",
    "Going live on Zoom without pants on.",
    "Eating toenail clippings.",
    "Using balloons as boobies.",
    "My dang kids.",
    "Squeezing a lemon into my eye.",
    "Ellen.",
    "Uncle Bob.",
    "Steakhouse.",
    "Dwayne \"The Rock\" Johnson.",
    "A baby with a full mustache.",
    "Eating a whole roll of toilet paper.",
    "The bacon.",
    "Falling off a mountain.",
    "Person milk.",
    "Pink eye.",
    "Pork.",
    "The government.",
    "JOHN CENAAAA!",
    "Nothing.",
    "GOOOAAALLLL!!!",
    "Mom's new haircut.",
    "Happy daddies with happy sandals.",
    "Giggling and farting and slurping milkshakes.",
    "Ice pee.",
    "Obama.",
    "Twerking.",
    "Reading my sister's diary.",
    "The ice cream man.",
    "Love.",
    "Raisins.",
    "Living in the dumpster.",
    "Having a baby.",
    "Shoplifting.",
    "The dentist.",
    "Aunt Linda.",
    "One tough mama.",
    "Releasing the falcons!",
    "Flushing myself down the toilet.",
    "Fire farts.",
    "Lice.",
    "Anti-vaxxers.",
    "Wiping my butt.",
    "Beyoncé.",
    "A truck.",
    "Only beans.",
    "Legs.",
    "Feminism.",
    "Lighting stuff on fire.",
    "Turning 40.",
    "Getting a skull tattoo.",
    "The longest tongue in the world.",
    "Josh.",
    "Locking Mother in the pantry.",
    "Ariana Grande.",
    "Puber ty.",
    "A glorious beard.",
    "A dog that stares into eternal nothingness.",
    "Dumbness.",
    "Flamin' Hot Cheetos.",
    "Peeing in a glorious golden arc.",
    "My ex-wife.",
    "Using my butt as a microwave.",
    "Glen's fabulous body.",
    "Gluten.",
    "Who cares.",
    "Many wolves.",
    "A butt that eats underwear.",
    "Poo-poo.",
    "Mooing.",
    "Meat blindness.",
    "Punching everyone.",
    "Swords.",
    "Kevin's mom.",
    "Getting scalded hot beans.",
    "Chest hair.",
    "My annoying sister.",
    "Getting slapped with a fish.",
    "Harry Potter.",
    "Peeing sand.",
    "Guacamole.",
    "Getting naked.",
    "A super angry cat I found outside.",
    "Learn more at www.",
    "SlappySpatchy.com.",
    "A pregnant person.",
    "Grandma panties.",
    "Having no bones.",
    "Famous peanut scientist George Washington Car ver.",
    "A hug.",
    "The Dark Lord.",
    "Being super serious right now.",
    "Freeing a fart from its butt prison.",
    "An order of mozzarella sticks.",
    "Fake news.",
    "The baby.",
    "Like a million alligators.",
    "Beer.",
    "Spit.",
    "The fifth graders.",
    "Licking a goat.",
    "A flamethrower.",
    "Drama!",
    "Old Jim's Steamy Butt Sauce.",
    "Going to the emergency room.",
    "Girls.",
    "A Pringle.",
    "Never showering.",
    "Hunky men.",
    "The gym teacher.",
    "Coming back from the dead.",
    "Burning books.",
    "Deep-frying Dad's laptop.",
    "Violating the dress code.",
    "Practicing kissing.",
    "Slowly turning into cheese.",
    "Ear wax.",
    "Knives.",
    "Stuff.",
    "Taking a selfie.",
    "Dancing with my son.",
    "Punching a guy through a wall.",
    "Nipples.",
    "Cat pee.",
    "Cringe. Billie Eilish.",
    "Really bad Dad jokes.",
    "Elegant party hats.",
    "Santa Claus.",
    "The gluteus maximus.",
    "B a by Yo d a.",
    "Peeing in the cat's litter box.",
    "A big sad dragon with no friends.",
    "A big whiny cry-baby.",
    "Seymour Butts.",
    "The bus driver.",
    "Getting run over by a train.",
    "Spinning and barfing.",
    "Some freakin' privacy.",
    "Butt hair.",
    "Having many husbands.",
    "Coffee.",
    "Anime.",
    "The sweet honking of Karen's bassoon.",
    "Being dead.",
    "Pooping barf forever.",
    "FOOOOD FIIIIIIIIIIIIIIIIIGHT!!!",
    "Wearing high heels.",
    "Getting trampled by horses.",
    "The babysitter.",
    "The lunch lady.",
    "Peeing on my poopy.",
    "Not wearing pants.",
    "Finding Waldo.",
    "Going around sniffing people's armpits.",
    "Stealing Mom's credit card.",
    "Diaper beans.",
    "Cigarettes.",
    "Getting my ponytail stuck in my butt.",
    "Looking into people's windows.",
    "Sucking at life.",
    "Evil.",
    "A big rock.",
    "Rubbing lotion on a hairless cat.",
    "Goblins.",
    "Nasty Cousin Amber.",
    "Tongue kissing.",
    "Abraham Lincoln.",
    "Feet.",
    "Sadness.",
    "Going beast mode.",
    "An owl that hates you.",
    "A doll that pees real pee!",
    "A naked lady in a painting.",
    "Chunks.",
    "Some weird guy.",
    "Getting a girlfriend.",
    "Falling in love with a hot dog.",
    "Throwing stuff at other stuff.",
    "Hogs.",
    "A turd that just won't flush.",
    "Showing everyone my butt.",
    "Math.",
    "Pee-pee.",
    "Dinner.",
    "Butthole.",
    "Smelling like onions.",
    "Being fake.",
    "Peer pressure.",
    "Peeing in my backpack.",
    "Bad parenting.",
    "Mom's butt.",
    "One weird lookin' toe.",
    "Yo u.",
    "Boys.",
    "Sitting on a cake.",
    "Teaching a chicken to kill.",
    "The middle finger.",
    "A bra.",
    "Being famous on YouTube.",
    "Cream.",
    "Balls.",
    "Having no friends.",
    "Peeing into everyone's mouth.",
    "Gluing my butt cheeks together.",
    "Total crap.",
    "Cool sunglasses.",
    "Snot bubbles.",
    "Doing crimes and going to jail.",
    "Aliens.",
    "School.",
    "A cow.",
    "The terrible winter of 1609.",
    "Getting sucked into a jet engine.",
    "Not breathing.",
    "Licking a used band-aid.",
    "Braiding my armpit hair.",
    "Waking up inside of a spider web.",
    "An eggy smell.",
    "Getting hit by an airplane."
  ]
}
